{
  "$schema": "https://aka.ms/winget-packages.schema.2.0.json",
  "CreationDate": "2025-10-04T22:14:29.114-00:00",
  "Sources": [
    {
      "Packages": [
        
        {"PackageIdentifier": "Discord.Discord.Canary"},
        {"PackageIdentifier": "UCBerkeley.BOINC"},
        {"PackageIdentifier": "LGUG2Z.komorebi"},
        {"PackageIdentifier": "LGUG2Z.whkd"},
        {"PackageIdentifier": "SoftDeluxe.FreeDownloadManager"},
        {"PackageIdentifier": "Google.GoogleDrive"},
        {"PackageIdentifier": "Microsoft.Edge.Canary"},
        {"PackageIdentifier": "Microsoft.PCManager.Beta"},
        {"PackageIdentifier": "Microsoft.WindowsPCHealthCheck"},
        {"PackageIdentifier": "Tailscale.Tailscale"},
        {"PackageIdentifier": "spacedrive.Spacedrive"},
        {"PackageIdentifier": "Giorgiotani.Peazip"},
        {"PackageIdentifier": "Microsoft.WSL"},
        {"PackageIdentifier": "NickJohn.EnergyStarX"},
        {"PackageIdentifier": "Notion.Notion"},
        {"PackageIdentifier": "OBSProject.OBSStudio.Pre-release"},
        {"PackageIdentifier": "LizardByte.Sunshine"},
        {"PackageIdentifier": "Docker.DockerCLI"}
        
      ],
      "SourceDetails": {
        "Argument": "https://cdn.winget.microsoft.com/cache",
        "Identifier": "Microsoft.Winget.Source_8wekyb3d8bbwe",
        "Name": "winget",
        "Type": "Microsoft.PreIndexed.Package"
      }
    }
  ],
  "WinGetVersion": "1.12.240-preview"
}
